duckbridge/__init__.py
duckbridge/client/__init__.py
duckbridge/client/client.py
duckbridge/client/duckbridge_client.py
duckbridge/constant/__init__.py
duckbridge/constant/constants.py
duckbridge/server/__init__.py
duckbridge/server/duckbridge_server.py
duckbridge/server/server.py
duckbridge-0.4.1.dist-info/LICENSE
duckbridge-0.4.1.dist-info/METADATA
duckbridge-0.4.1.dist-info/WHEEL
duckbridge-0.4.1.dist-info/RECORD
